blackbit_pkg/__init__.py
blackbit_pkg/launcher.py
blackbit_pkg/data/blackbit.exe
blackbit-1.1.0.dist-info/METADATA
blackbit-1.1.0.dist-info/WHEEL
blackbit-1.1.0.dist-info/entry_points.txt
blackbit-1.1.0.dist-info/top_level.txt
blackbit-1.1.0.dist-info/RECORD
