Metadata-Version: 2.4
Name: blackbit
Version: 1.1.0
Summary: BlackBit standalone tool
Author: BlackBit
Dynamic: author
Dynamic: summary
